vat/__init__.py
vat/cli.py
vat/platform.py
vat/stix_taxii.py
vat/vectra.py
vectra_api_tools-3.3.1.dist-info/METADATA
vectra_api_tools-3.3.1.dist-info/WHEEL
vectra_api_tools-3.3.1.dist-info/licenses/LICENSE.txt
vectra_api_tools-3.3.1.dist-info/RECORD
