Metadata-Version: 2.3
Name: vectra-api-tools
Version: 3.3.1
Summary: Vectra API client library
Project-URL: Homepage, https://github.com/vectranetworks/vectra_api_tools
Author-email: Brandon Wyatt <bwyatt@vectra.ai>, Vectra <tme@vectra.ai>
License-File: LICENSE.txt
Classifier: License :: OSI Approved :: Apache Software License
Classifier: Operating System :: OS Independent
Classifier: Programming Language :: Python :: 3
Requires-Python: >=3.10
Requires-Dist: backoff
Requires-Dist: cabby
Requires-Dist: pytz
Requires-Dist: requests
Requires-Dist: stix
